{"is_source_file": true, "format": "Java", "description": "This file defines an enum representing different statuses of an invoice in the system.", "external_files": [], "external_methods": [], "published": ["com.example.invoicebackend.model.enums.InvoiceStatus"], "classes": [{"name": "InvoiceStatus", "description": "Enum for invoice workflow status values aligned with V1 migration."}], "methods": [], "calls": [], "search-terms": ["InvoiceStatus", "Invoice workflow status", "enum", "com.example.invoicebackend.model.enums"], "state": 2, "file_id": 25, "knowledge_revision": 58, "git_revision": "", "hash": "db4ff765514db2206831f63ed9766f8c", "format-version": 4, "code-base-name": "invoice_backend", "filename": "invoice_backend/src/main/java/com/example/invoicebackend/model/enums/InvoiceStatus.java", "revision_history": [{"58": ""}]}